{
  "Phase 1": {
    "character": "Pre-COVID, low vol, steady rates",
    "test_bars": 2405,
    "static": {
      "mae": 0.001056,
      "dir_acc": 0.5963,
      "f1": 0.6029,
      "precision": 0.6051,
      "recall": 0.6007
    },
    "retrained": {
      "mae": 0.001056,
      "dir_acc": 0.5963,
      "f1": 0.6029,
      "precision": 0.6051,
      "recall": 0.6007
    },
    "shiftguard": {
      "mae": 0.001056,
      "dir_acc": 0.5963,
      "f1": 0.6029,
      "precision": 0.6051,
      "recall": 0.6007
    },
    "shap_action": "RETRAINED (dominant: sentiment)",
    "dominant_group": "sentiment",
    "mae_improvement_retrained": 0.0,
    "dir_improvement_retrained": 0.0,
    "mae_improvement_shap": 0.0,
    "dir_improvement_shap": 0.0
  },
  "Phase 2": {
    "character": "COVID crash, recovery, Fed hike cycle",
    "test_bars": 2418,
    "static": {
      "mae": 0.001467,
      "dir_acc": 0.5943,
      "f1": 0.5806,
      "precision": 0.5856,
      "recall": 0.5757
    },
    "retrained": {
      "mae": 0.001499,
      "dir_acc": 0.5964,
      "f1": 0.5941,
      "precision": 0.5831,
      "recall": 0.6054
    },
    "shiftguard": {
      "mae": 0.001499,
      "dir_acc": 0.5964,
      "f1": 0.5941,
      "precision": 0.5831,
      "recall": 0.6054
    },
    "shap_action": "RETRAINED (dominant: sentiment)",
    "dominant_group": "sentiment",
    "mae_improvement_retrained": -2.18,
    "dir_improvement_retrained": 0.35,
    "mae_improvement_shap": -2.18,
    "dir_improvement_shap": 0.35
  },
  "Phase 3": {
    "character": "Post-hike, BOJ shift, gold rally, tariffs",
    "test_bars": 2002,
    "static": {
      "mae": 0.001199,
      "dir_acc": 0.5969,
      "f1": 0.6023,
      "precision": 0.605,
      "recall": 0.5996
    },
    "retrained": {
      "mae": 0.001206,
      "dir_acc": 0.5824,
      "f1": 0.5803,
      "precision": 0.594,
      "recall": 0.5672
    },
    "shiftguard": {
      "mae": 0.001206,
      "dir_acc": 0.5824,
      "f1": 0.5803,
      "precision": 0.594,
      "recall": 0.5672
    },
    "shap_action": "RETRAINED (dominant: sentiment)",
    "dominant_group": "sentiment",
    "mae_improvement_retrained": -0.58,
    "dir_improvement_retrained": -2.43,
    "mae_improvement_shap": -0.58,
    "dir_improvement_shap": -2.43
  }
}